mockingpy/__init__.py
mockingpy/default_config.yml
mockingpy/mocking.py
mockingpy/plotter.py
mockingpy-1.0.0.dist-info/LICENCE
mockingpy-1.0.0.dist-info/METADATA
mockingpy-1.0.0.dist-info/WHEEL
mockingpy-1.0.0.dist-info/top_level.txt
mockingpy-1.0.0.dist-info/RECORD
